MANIFEST.in
setup.py
bills_score.egg-info/PKG-INFO
bills_score.egg-info/SOURCES.txt
bills_score.egg-info/dependency_links.txt
bills_score.egg-info/entry_points.txt
bills_score.egg-info/not-zip-safe
bills_score.egg-info/requires.txt
bills_score.egg-info/top_level.txt
bills_scoring/__init__.py
bills_scoring/bills_model.py
bills_scoring/cbci_wrapper.py
bills_scoring/hug_api.py
bills_scoring/settings.py
bills_scoring/user_schema_db.py
bills_scoring/win_serve.py
bills_scoring/dat/__init__.py
bills_scoring/dat/dist_M.csv
bills_scoring/dat/dist_Q.csv