Metadata-Version: 1.2
Name: bills-score
Version: 0.0.1
Summary: Bills Scoring
Home-page: UNKNOWN
Author: merlinsbeard
Author-email: bjpaat@dailywarrior.ph
License: UNKNOWN
Platform: UNKNOWN
Requires-Python: >=3.4
